README
setup.py
django_fast_fixtures.egg-info/PKG-INFO
django_fast_fixtures.egg-info/SOURCES.txt
django_fast_fixtures.egg-info/dependency_links.txt
django_fast_fixtures.egg-info/requires.txt
django_fast_fixtures.egg-info/top_level.txt
fast_fixtures/__init__.py
fast_fixtures/migrator.py
fast_fixtures/models.py
fast_fixtures/serializers.py
fast_fixtures/management/__init__.py
fast_fixtures/management/commands/__init__.py
fast_fixtures/management/commands/dumpdata.py
fast_fixtures/management/commands/loaddata.py