Metadata-Version: 1.0
Name: django-fast-fixtures
Version: 0.7
Summary: Replace dumpdata and loaddata with migration aware fixture commands.
Home-page: https://github.com/doctormo/django-fast-fixtures
Author: Martin Owens
Author-email: doctormo@gmail.com
License: LGPLv3
Platform: linux
